db4e/App.py
db4e/Constants/DButton.py
db4e/Constants/DDebug.py
db4e/Constants/DDef.py
db4e/Constants/DDir.py
db4e/Constants/DElem.py
db4e/Constants/DField.py
db4e/Constants/DFile.py
db4e/Constants/DForm.py
db4e/Constants/DJob.py
db4e/Constants/DLabel.py
db4e/Constants/DMethod.py
db4e/Constants/DMining.py
db4e/Constants/DModule.py
db4e/Constants/DMongo.py
db4e/Constants/DOps.py
db4e/Constants/DPane.py
db4e/Constants/DPlaceholder.py
db4e/Constants/DSelect.py
db4e/Constants/DStatus.py
db4e/Constants/DSystemD.py
db4e/Constants/__init__.py
db4e/Db4E.tcss
db4e/Messages/Db4eMsg.py
db4e/Messages/Quit.py
db4e/Messages/RefreshNavPane.py
db4e/Messages/UpdateTopBar.py
db4e/Messages/__init__.py
db4e/Modules/BootstrapMgr.py
db4e/Modules/Components.py
db4e/Modules/ConfigMgr.py
db4e/Modules/ConstGroup.py
db4e/Modules/Db4E.py
db4e/Modules/Db4ELogger.py
db4e/Modules/Db4ESystemD.py
db4e/Modules/DbCache.py
db4e/Modules/DbMgr.py
db4e/Modules/DeplClient.py
db4e/Modules/DeplMgr.py
db4e/Modules/HealthCache.py
db4e/Modules/HealthMgr.py
db4e/Modules/Helper.py
db4e/Modules/InstallMgr.py
db4e/Modules/InternalP2Pool.py
db4e/Modules/Job.py
db4e/Modules/JobQueue.py
db4e/Modules/LocalSoftwareSystem.py
db4e/Modules/MessageRouter.py
db4e/Modules/MiningDb.py
db4e/Modules/MiningETL.py
db4e/Modules/MoneroD.py
db4e/Modules/MoneroDRemote.py
db4e/Modules/OpsDb.py
db4e/Modules/OpsMgr.py
db4e/Modules/P2Pool.py
db4e/Modules/P2PoolRemote.py
db4e/Modules/P2PoolWatcher.py
db4e/Modules/PaneCatalogue.py
db4e/Modules/PaneMgr.py
db4e/Modules/SQLMgr.py
db4e/Modules/SoftwareSystem.py
db4e/Modules/XMRig.py
db4e/Modules/XMRigRemote.py
db4e/Modules/__init__.py
db4e/Panes/ChainBlocksFoundPane.py
db4e/Panes/ChainHashratesPane.py
db4e/Panes/ChainPane.py
db4e/Panes/Db4EPane.py
db4e/Panes/DonationsPane.py
db4e/Panes/InitialSetupPane.py
db4e/Panes/LogViewPane.py
db4e/Panes/MoneroDPane.py
db4e/Panes/MoneroDRemotePane.py
db4e/Panes/P2PoolHashratesPane.py
db4e/Panes/P2PoolPane.py
db4e/Panes/P2PoolRemotePane.py
db4e-0.48.1.dist-info/METADATA
db4e-0.48.1.dist-info/WHEEL
db4e-0.48.1.dist-info/entry_points.txt
db4e-0.48.1.dist-info/licenses/LICENSE
db4e-0.48.1.dist-info/RECORD
