Metadata-Version: 2.4
Name: db4e
Version: 0.48.1
Summary: A unified Monero XMR mining dashboard for deployment, operation and real-time analytics.
License: GPL-3.0-or-later
License-File: LICENSE
Keywords: monero,mining,textual,dashboard,analytics
Author: Nadim-Daniel Ghaznavi
Author-email: nghaznavi@gmail.com
Requires-Python: >=3.10,<3.12
Classifier: Development Status :: 4 - Beta
Classifier: Environment :: Console
Classifier: Intended Audience :: Developers
Classifier: Intended Audience :: System Administrators
Classifier: License :: OSI Approved :: GNU General Public License v3 or later (GPLv3+)
Classifier: Operating System :: OS Independent
Classifier: Programming Language :: Python :: 3
Classifier: Programming Language :: Python :: 3.10
Classifier: Programming Language :: Python :: 3.11
Classifier: Topic :: System :: Monitoring
Requires-Dist: PyYAML (>=6.0.2,<7.0.0)
Requires-Dist: fastapi (>=0.119.0,<0.120.0)
Requires-Dist: httpx (>=0.28.1,<0.29.0)
Requires-Dist: loguru (>=0.7.3,<0.8.0)
Requires-Dist: myloginpath (>=0.0.4,<0.0.5)
Requires-Dist: orjson (>=3.10.15,<4.0.0)
Requires-Dist: plotext (>=5.3.2,<6.0.0)
Requires-Dist: psutil (>=7.0.0,<8.0.0)
Requires-Dist: pydantic (>=2.12.2,<3.0.0)
Requires-Dist: pymongo (>=4.13.2,<5.0.0)
Requires-Dist: pytest-asyncio (>=1.2.0,<2.0.0)
Requires-Dist: requests (>=2.32.3,<3.0.0)
Requires-Dist: rich (>=14.0.0,<15.0.0)
Requires-Dist: sqlite-utils (>=3.35,<4.0)
Requires-Dist: textual-dev (>=1.7.0,<2.0.0)
Requires-Dist: textual-plot (>=0.8.0,<0.9.0)
Requires-Dist: textual-plotext (>=1.0.1,<2.0.0)
Requires-Dist: textual[syntax] (>=6.0.0,<7.0.0)
Requires-Dist: tomli_w (>=1.2.0,<2.0.0)
Requires-Dist: uvicorn (>=0.37.0,<0.38.0)
Requires-Dist: zstandard (>=0.23.0,<0.24.0)
Project-URL: Homepage, https://github.com/NadimGhaznavi/Db4E
Project-URL: Repository, https://github.com/NadimGhaznavi/Db4E
